brasil.gov.tiles-2.0-py2.7-nspkg.pth
brasil/gov/tiles/__init__.py
brasil/gov/tiles/config.py
brasil/gov/tiles/configure.zcml
brasil/gov/tiles/interfaces.py
brasil/gov/tiles/logger.py
brasil/gov/tiles/profiles.zcml
brasil/gov/tiles/testing.py
brasil/gov/tiles/utils.py
brasil/gov/tiles/browser/__init__.py
brasil/gov/tiles/browser/configure.zcml
brasil/gov/tiles/browser/tileshare.pt
brasil/gov/tiles/browser/tileshare.py
brasil/gov/tiles/browser/static/README.rst
brasil/gov/tiles/browser/static/brasilgovtiles-7d5753d.css
brasil/gov/tiles/browser/static/brasilgovtiles-7d5753d.js
brasil/gov/tiles/browser/static/resources.pt
brasil/gov/tiles/browser/static/img/footer-arrow.png
brasil/gov/tiles/browser/static/img/footer-arrow_jpg.png
brasil/gov/tiles/browser/static/img/icon-camera-download.png
brasil/gov/tiles/browser/static/img/icon-carosel.png
brasil/gov/tiles/browser/static/img/icons-setas-min.png
brasil/gov/tiles/browser/static/img/icons-setas.png
brasil/gov/tiles/browser/static/img/image-download.png
brasil/gov/tiles/browser/static/img/image-zoom.png
brasil/gov/tiles/browser/static/img/jplayer.blue.monday.png
brasil/gov/tiles/browser/static/img/jplayer.blue.monday.seeking.gif
brasil/gov/tiles/browser/static/img/quote.png
brasil/gov/tiles/browser/static/img/readmorewhiteblue.png
brasil/gov/tiles/browser/static/img/seta_branca.png
brasil/gov/tiles/browser/static/img/sound-icon.png
brasil/gov/tiles/browser/static/img/sprite.png
brasil/gov/tiles/browser/static/img/tile-agenda.png
brasil/gov/tiles/browser/static/img/tile-albuns.png
brasil/gov/tiles/browser/static/img/tile-article.png
brasil/gov/tiles/browser/static/img/tile-audio.png
brasil/gov/tiles/browser/static/img/tile-audiogallery.png
brasil/gov/tiles/browser/static/img/tile-header.png
brasil/gov/tiles/browser/static/img/tile-media.png
brasil/gov/tiles/browser/static/img/tile-mediagallery.png
brasil/gov/tiles/browser/static/vendor/Jplayer.swf
brasil/gov/tiles/browser/static/vendor/galleria.classic.css
brasil.gov.tiles-2.0.dist-info/METADATA
brasil.gov.tiles-2.0.dist-info/WHEEL
brasil.gov.tiles-2.0.dist-info/entry_points.txt
brasil.gov.tiles-2.0.dist-info/namespace_packages.txt
brasil.gov.tiles-2.0.dist-info/top_level.txt
brasil.gov.tiles-2.0.dist-info/RECORD
