Metadata-Version: 2.1
Name: brasil.gov.tiles
Version: 2.0
Summary: Tiles para o Portal Padrão do Governo Federal
Home-page: https://github.com/plonegovbr/brasil.gov.tiles
Author: PloneGov.BR
Author-email: gov@plone.org.br
License: GPLv2
Keywords: plone tiles brasil gov
Platform: UNKNOWN
Classifier: Development Status :: 5 - Production/Stable
Classifier: Environment :: Web Environment
Classifier: Framework :: Plone
Classifier: Framework :: Plone :: 4.3
Classifier: Intended Audience :: Developers
Classifier: Intended Audience :: System Administrators
Classifier: License :: OSI Approved :: GNU General Public License v2 (GPLv2)
Classifier: Operating System :: OS Independent
Classifier: Programming Language :: JavaScript
Classifier: Programming Language :: Python
Classifier: Programming Language :: Python :: 2.7
Classifier: Topic :: Internet :: WWW/HTTP
Classifier: Topic :: Internet :: WWW/HTTP :: Dynamic Content
Classifier: Topic :: Multimedia
Classifier: Topic :: Software Development :: Libraries :: Python Modules
Requires-Dist: Acquisition
Requires-Dist: collective.cover
Requires-Dist: collective.nitf
Requires-Dist: collective.polls
Requires-Dist: plone.api
Requires-Dist: plone.app.uuid
Requires-Dist: plone.autoform
Requires-Dist: plone.memoize
Requires-Dist: plone.namedfile
Requires-Dist: plone.registry
Requires-Dist: plone.tiles
Requires-Dist: plone.app.imagecropping (<2.0b1)
Requires-Dist: Products.CMFPlone (>=4.3)
Requires-Dist: Products.CMFQuickInstallerTool
Requires-Dist: Products.GenericSetup
Requires-Dist: sc.embedder
Requires-Dist: setuptools
Requires-Dist: six
Requires-Dist: zope.component
Requires-Dist: zope.i18nmessageid
Requires-Dist: zope.interface
Requires-Dist: zope.schema
Provides-Extra: test
Requires-Dist: collective.cover[test] ; extra == 'test'
Requires-Dist: mock ; extra == 'test'
Requires-Dist: plone.api ; extra == 'test'
Requires-Dist: plone.app.referenceablebehavior ; extra == 'test'
Requires-Dist: plone.app.robotframework ; extra == 'test'
Requires-Dist: plone.app.testing[robot] ; extra == 'test'
Requires-Dist: plone.browserlayer ; extra == 'test'
Requires-Dist: plone.testing ; extra == 'test'
Requires-Dist: robotsuite ; extra == 'test'
